odoo8_addon_pos_analytic_by_config-8.0.1.0.0.99.dev11-py2.7-nspkg.pth
odoo8_addon_pos_analytic_by_config-8.0.1.0.0.99.dev11.dist-info/METADATA
odoo8_addon_pos_analytic_by_config-8.0.1.0.0.99.dev11.dist-info/RECORD
odoo8_addon_pos_analytic_by_config-8.0.1.0.0.99.dev11.dist-info/WHEEL
odoo8_addon_pos_analytic_by_config-8.0.1.0.0.99.dev11.dist-info/namespace_packages.txt
odoo8_addon_pos_analytic_by_config-8.0.1.0.0.99.dev11.dist-info/top_level.txt
odoo_addons/pos_analytic_by_config/README.rst
odoo_addons/pos_analytic_by_config/__init__.py
odoo_addons/pos_analytic_by_config/__openerp__.py
odoo_addons/pos_analytic_by_config/i18n/ca.po
odoo_addons/pos_analytic_by_config/i18n/de.po
odoo_addons/pos_analytic_by_config/i18n/el_GR.po
odoo_addons/pos_analytic_by_config/i18n/es.po
odoo_addons/pos_analytic_by_config/i18n/es_MX.po
odoo_addons/pos_analytic_by_config/i18n/fi.po
odoo_addons/pos_analytic_by_config/i18n/fr.po
odoo_addons/pos_analytic_by_config/i18n/pos_analytic_by_config.pot
odoo_addons/pos_analytic_by_config/i18n/pt_BR.po
odoo_addons/pos_analytic_by_config/i18n/sk_SK.po
odoo_addons/pos_analytic_by_config/i18n/sl.po
odoo_addons/pos_analytic_by_config/i18n/zh_CN.po
odoo_addons/pos_analytic_by_config/models/__init__.py
odoo_addons/pos_analytic_by_config/models/pos_config.py
odoo_addons/pos_analytic_by_config/models/pos_order.py
odoo_addons/pos_analytic_by_config/static/description/icon.png
odoo_addons/pos_analytic_by_config/tests/__init__.py
odoo_addons/pos_analytic_by_config/tests/test_pos_analytic_by_config.py
odoo_addons/pos_analytic_by_config/views/pos_config_view.xml
